lambdatest_selenium_driver/__init__.py
lambdatest_selenium_driver/full_page_screenshot_util.py
lambdatest_selenium_driver/smartui.py
lambdatest_selenium_driver/smartui_app_snapshot.py
lambdatest_selenium_driver/version.py
lambdatest_selenium_driver-1.0.9.dist-info/METADATA
lambdatest_selenium_driver-1.0.9.dist-info/WHEEL
lambdatest_selenium_driver-1.0.9.dist-info/top_level.txt
lambdatest_selenium_driver-1.0.9.dist-info/RECORD
