Metadata-Version: 2.4
Name: lambdatest-selenium-driver
Version: 1.0.9
Summary: Python Selenium SDK for testing with Smart UI
Home-page: https://github.com/LambdaTest/lambdatest-python-sdk
Author: LambdaTest <keys@lambdatest.com>
License: MIT
Keywords: lambdatest python selenium sdk
Classifier: Development Status :: 5 - Production/Stable
Classifier: Programming Language :: Python :: 3
Classifier: Natural Language :: English
Classifier: License :: OSI Approved :: MIT License
Requires-Python: >=3.6
Requires-Dist: selenium>=3
Requires-Dist: lambdatest-sdk-utils>=1.0.5
Dynamic: author
Dynamic: classifier
Dynamic: description
Dynamic: description-content-type
Dynamic: home-page
Dynamic: keywords
Dynamic: license
Dynamic: requires-dist
Dynamic: requires-python
Dynamic: summary
